gwsproto/__init__.py
gwsproto/conversions/temperature.py
gwsproto/data_classes/__init__.py
gwsproto/data_classes/components/__init__.py
gwsproto/data_classes/components/ads111x_based_component.py
gwsproto/data_classes/components/component.py
gwsproto/data_classes/components/dfr_component.py
gwsproto/data_classes/components/electric_meter_component.py
gwsproto/data_classes/components/fibaro_smart_implant_component.py
gwsproto/data_classes/components/hubitat_component.py
gwsproto/data_classes/components/hubitat_poller_component.py
gwsproto/data_classes/components/i2c_multichannel_dt_relay_component.py
gwsproto/data_classes/components/pico_btu_meter_component.py
gwsproto/data_classes/components/pico_flow_module_component.py
gwsproto/data_classes/components/pico_tank_module_component.py
gwsproto/data_classes/components/resistive_heater_component.py
gwsproto/data_classes/components/rest_poller_component.py
gwsproto/data_classes/components/sim_pico_tank_module_component.py
gwsproto/data_classes/components/web_server_component.py
gwsproto/data_classes/data_channel.py
gwsproto/data_classes/derived_channel.py
gwsproto/data_classes/hardware_layout.py
gwsproto/data_classes/house_0_layout.py
gwsproto/data_classes/house_0_names.py
gwsproto/data_classes/layout_lite_dc.py
gwsproto/data_classes/resolver.py
gwsproto/data_classes/sh_node.py
gwsproto/data_classes/telemetry_tuple.py
gwsproto/decoders.py
gwsproto/default_decoders.py
gwsproto/enums/__init__.py
gwsproto/enums/actor_class.py
gwsproto/enums/aquastat_control.py
gwsproto/enums/change_aquastat_control.py
gwsproto/enums/change_heat_pump_control.py
gwsproto/enums/change_heatcall_source.py
gwsproto/enums/change_keep_send.py
gwsproto/enums/change_primary_pump_control.py
gwsproto/enums/change_relay_pin.py
gwsproto/enums/change_relay_state.py
gwsproto/enums/change_store_flow_relay.py
gwsproto/enums/flow_manifold_variant.py
gwsproto/enums/fsm_action_type.py
gwsproto/enums/fsm_report_type.py
gwsproto/enums/gpm_from_hz_method.py
gridworks_scada_protocol-1.2.1.dist-info/WHEEL
gridworks_scada_protocol-1.2.1.dist-info/METADATA
gridworks_scada_protocol-1.2.1.dist-info/RECORD
