Metadata-Version: 2.3
Name: gridworks-scada-protocol
Version: 1.2.1
Summary: Data structures used in messages between gridworks-scada devices, the gridworks Ltn and the gridworks-admin monitoring CLI.
Author: Jessica Millar
Author-email: Jessica Millar <jmillar@gridworks-consulting.com>
Requires-Dist: gridworks-protocol>=1.3.3,<2.0.0
Requires-Dist: transitions>=0.9.3
Requires-Python: >=3.11
